setup.py
jfpackage/__init__.py
jfpackage/soph_funcs.py
jfpackage.egg-info/PKG-INFO
jfpackage.egg-info/SOURCES.txt
jfpackage.egg-info/dependency_links.txt
jfpackage.egg-info/not-zip-safe
jfpackage.egg-info/top_level.txt