Metadata-Version: 1.0
Name: jfpackage
Version: 0.2
Summary: Jae's first package ever. Second version.
Home-page: UNKNOWN
Author: Jae Hyeon Lee
Author-email: jaekor@gmail.com
License: Harvard
Platform: UNKNOWN
